d6tjoin/__init__.py
d6tjoin/pre.py
d6tjoin/smart_join.py
d6tjoin/top1.py
d6tjoin/utils.py
d6tjoin-0.2.1.dist-info/METADATA
d6tjoin-0.2.1.dist-info/WHEEL
d6tjoin-0.2.1.dist-info/top_level.txt
d6tjoin-0.2.1.dist-info/RECORD
