Metadata-Version: 2.1
Name: d6tjoin
Version: 0.2.1
Summary: Easily join python pandas dataframes
Home-page: https://github.com/d6t/d6tjoin
Author: DataBolt Team
Author-email: support@databolt.tech
License: MIT
Platform: UNKNOWN
Requires-Python: >=3.6
Requires-Dist: numpy
Requires-Dist: pandas
Requires-Dist: jellyfish
Requires-Dist: joblib
Requires-Dist: d6tstack
